stuy_utils/__init__.py
stuy_utils/errors.py
stuy_utils/schedule.py
stuy_utils/data/bell_schedule.csv
stuy_utils/data/term_days.csv
stuy_utils/tests/__init__.py
stuy_utils/tests/schedule_test.py
stuy_utils-0.0.1.data/data/bell_schedule/bell_schedule.csv
stuy_utils-0.0.1.data/data/term_days/term_days.csv
stuy_utils-0.0.1.dist-info/LICENSE
stuy_utils-0.0.1.dist-info/METADATA
stuy_utils-0.0.1.dist-info/WHEEL
stuy_utils-0.0.1.dist-info/top_level.txt
stuy_utils-0.0.1.dist-info/RECORD
